ESD/__init__.py
ESD/cacert.pem
ESD/key.ini
ESD/subs-test.esd
ESD/subs.esd
ESD-0.0.29.dist-info/LICENSE
ESD-0.0.29.dist-info/METADATA
ESD-0.0.29.dist-info/WHEEL
ESD-0.0.29.dist-info/entry_points.txt
ESD-0.0.29.dist-info/top_level.txt
ESD-0.0.29.dist-info/RECORD
