Metadata-Version: 2.1
Name: ESD
Version: 0.0.29
Summary: Enumeration Sub Domains(枚举子域名)
Home-page: https://github.com/FeeiCN/ESD
Author: Feei
Author-email: feei@feei.cn
License: UNKNOWN
Platform: UNKNOWN
Classifier: Topic :: Security
Classifier: Programming Language :: Python :: 3
Classifier: License :: OSI Approved :: GNU General Public License v3 (GPLv3)
